finomeny_logger/__init__.py
finomeny_logger/logger.py
finomeny_logger/py.typed
finomeny_logger/schemas.py
finomeny_logger-1.0.0.dist-info/METADATA
finomeny_logger-1.0.0.dist-info/WHEEL
finomeny_logger-1.0.0.dist-info/licenses/LICENSE
finomeny_logger-1.0.0.dist-info/RECORD
