Metadata-Version: 2.4
Name: finomeny-logger
Version: 1.0.0
Summary: Production-ready structured logging library for Finomeny services
Project-URL: Homepage, https://github.com/FinomenyTech/finomeny-logger
Project-URL: Repository, https://github.com/FinomenyTech/finomeny-logger
Project-URL: Documentation, https://finomeny-logger.readthedocs.io
Project-URL: Changelog, https://github.com/FinomenyTech/finomeny-logger/blob/main/CHANGELOG.md
Project-URL: Issues, https://github.com/FinomenyTech/finomeny-logger/issues
Author-email: Finomeny Engineering <nesi@finomeny.es>
License-Expression: MIT
License-File: LICENSE
Keywords: aws,fintech,logging,observability,structured-logging
Classifier: Development Status :: 5 - Production/Stable
Classifier: Intended Audience :: Developers
Classifier: License :: OSI Approved :: MIT License
Classifier: Operating System :: OS Independent
Classifier: Programming Language :: Python :: 3
Classifier: Programming Language :: Python :: 3.8
Classifier: Programming Language :: Python :: 3.9
Classifier: Programming Language :: Python :: 3.10
Classifier: Programming Language :: Python :: 3.11
Classifier: Programming Language :: Python :: 3.12
Classifier: Topic :: Software Development :: Libraries :: Python Modules
Classifier: Topic :: System :: Logging
Requires-Python: >=3.8
Requires-Dist: typing-extensions>=4.0.0; python_version < '3.10'
Provides-Extra: dev
Requires-Dist: black>=23.0.0; extra == 'dev'
Requires-Dist: flake8>=6.0.0; extra == 'dev'
Requires-Dist: isort>=5.12.0; extra == 'dev'
Requires-Dist: mypy>=1.0.0; extra == 'dev'
Requires-Dist: pre-commit>=3.0.0; extra == 'dev'
Requires-Dist: pytest-cov>=4.0.0; extra == 'dev'
Requires-Dist: pytest-mock>=3.10.0; extra == 'dev'
Requires-Dist: pytest>=7.0.0; extra == 'dev'
Provides-Extra: test
Requires-Dist: moto>=4.2.0; extra == 'test'
Requires-Dist: pytest-cov>=4.0.0; extra == 'test'
Requires-Dist: pytest-mock>=3.10.0; extra == 'test'
Requires-Dist: pytest>=7.0.0; extra == 'test'
